odoo/addons/pos_loyalty/README.rst
odoo/addons/pos_loyalty/__init__.py
odoo/addons/pos_loyalty/__manifest__.py
odoo/addons/pos_loyalty/demo/templates.xml
odoo/addons/pos_loyalty/i18n/ca.po
odoo/addons/pos_loyalty/i18n/es.po
odoo/addons/pos_loyalty/i18n/fr.po
odoo/addons/pos_loyalty/i18n/hr_HR.po
odoo/addons/pos_loyalty/i18n/it.po
odoo/addons/pos_loyalty/i18n/nl_NL.po
odoo/addons/pos_loyalty/i18n/pos_loyalty.pot
odoo/addons/pos_loyalty/models/__init__.py
odoo/addons/pos_loyalty/models/loyalty_program.py
odoo/addons/pos_loyalty/models/loyalty_reward.py
odoo/addons/pos_loyalty/models/loyalty_rule.py
odoo/addons/pos_loyalty/models/pos_config.py
odoo/addons/pos_loyalty/models/pos_order.py
odoo/addons/pos_loyalty/models/pos_order_line.py
odoo/addons/pos_loyalty/models/res_partner.py
odoo/addons/pos_loyalty/readme/CONFIGURE.rst
odoo/addons/pos_loyalty/readme/CONTRIBUTORS.rst
odoo/addons/pos_loyalty/readme/DESCRIPTION.rst
odoo/addons/pos_loyalty/readme/USAGE.rst
odoo/addons/pos_loyalty/security/ir.model.access.csv
odoo/addons/pos_loyalty/static/description/icon.png
odoo/addons/pos_loyalty/static/description/index.html
odoo/addons/pos_loyalty/static/src/css/pos.css
odoo/addons/pos_loyalty/static/src/js/pos.js
odoo/addons/pos_loyalty/static/src/js/tests.js
odoo/addons/pos_loyalty/static/src/xml/pos.xml
odoo/addons/pos_loyalty/tests/__init__.py
odoo/addons/pos_loyalty/tests/test_pos_loyalty.py
odoo/addons/pos_loyalty/views/loyalty_program_view.xml
odoo/addons/pos_loyalty/views/loyalty_reward_view.xml
odoo/addons/pos_loyalty/views/loyalty_rule_view.xml
odoo/addons/pos_loyalty/views/pos_config_view.xml
odoo/addons/pos_loyalty/views/pos_order_view.xml
odoo/addons/pos_loyalty/views/res_partner_view.xml
odoo/addons/pos_loyalty/views/templates.xml
odoo11_addon_pos_loyalty-11.0.1.0.1.dist-info/METADATA
odoo11_addon_pos_loyalty-11.0.1.0.1.dist-info/WHEEL
odoo11_addon_pos_loyalty-11.0.1.0.1.dist-info/top_level.txt
odoo11_addon_pos_loyalty-11.0.1.0.1.dist-info/RECORD
